eca/__init__.py
eca/models.py
eca/orchestrator.py
eca/workspace.py
eca/adapters/__init__.py
eca/adapters/base.py
eca/adapters/json_adapter.py
eca/adapters/postgres_adapter.py
eca/adapters/redis_adapter.py
eca/attention/__init__.py
eca/attention/base.py
eca/attention/semantic_attention.py
eca/attention/vector_attention.py
eca/cognitive/__init__.py
eca/cognitive/activation.py
eca/cognitive/graph_attention.py
eca/cognitive/repository.py
eca/cognitive/types.py
eca/database/schema.py
eca/memory/__init__.py
eca/memory/rules_loader.py
eca/memory/types.py
eca/memory/utils.py
eca/prompts/__init__.py
eca/prompts/meta_prompt_template_en.txt
eca/prompts/meta_prompt_template_pt_br.txt
eca_lib-0.1.8.dist-info/licenses/LICENSE
eca_lib-0.1.8.dist-info/METADATA
eca_lib-0.1.8.dist-info/WHEEL
eca_lib-0.1.8.dist-info/top_level.txt
eca_lib-0.1.8.dist-info/RECORD
