Metadata-Version: 2.4
Name: eca-lib
Version: 0.1.8
Summary: Uma biblioteca Python para implementar a arquitetura de Engenharia de Contexto Aumentada (ECA).
Author-email: coagentis <contato@coagentis.com.br>
Project-URL: Homepage, https://github.com/coagentis/eca-lib
Project-URL: Bug Tracker, https://github.com/coagentis/eca-lib/issues
Classifier: Development Status :: 3 - Alpha
Classifier: Intended Audience :: Developers
Classifier: Topic :: Software Development :: Libraries :: Python Modules
Classifier: Topic :: Scientific/Engineering :: Artificial Intelligence
Classifier: License :: OSI Approved :: MIT License
Classifier: Operating System :: OS Independent
Classifier: Programming Language :: Python :: 3
Classifier: Programming Language :: Python :: 3.8
Classifier: Programming Language :: Python :: 3.9
Classifier: Programming Language :: Python :: 3.10
Classifier: Programming Language :: Python :: 3.11
Requires-Python: >=3.8
License-File: LICENSE
Provides-Extra: redis
Requires-Dist: redis>=5.0.0; extra == "redis"
Provides-Extra: postgres
Requires-Dist: psycopg2-binary>=2.9.0; extra == "postgres"
Requires-Dist: pgvector>=0.2.0; extra == "postgres"
Requires-Dist: SQLAlchemy>=2.0.0; extra == "postgres"
Provides-Extra: all
Requires-Dist: eca-lib[redis]; extra == "all"
Requires-Dist: eca-lib[postgres]; extra == "all"
Dynamic: license-file
